dp/__init__.py
dp/agent/__init__.py
dp/agent/adapter/adk/__init__.py
dp/agent/adapter/adk/storage_artifact_service.py
dp/agent/adapter/adk/utils.py
dp/agent/adapter/adk/client/__init__.py
dp/agent/adapter/adk/client/calculation_mcp_tool.py
dp/agent/adapter/camel/__init__.py
dp/agent/adapter/camel/client/__init__.py
dp/agent/adapter/camel/client/calculation_mcp_client.py
dp/agent/cli/__init__.py
dp/agent/cli/cli.py
dp/agent/cli/templates/__init__.py
dp/agent/cli/templates/main.py.template
dp/agent/cli/templates/calculation/simple.py.template
dp/agent/cli/templates/device/tescan_device.py.template
dp/agent/cli/templates/ui/__init__.py
dp/agent/cli/templates/ui/test_download.py
dp/agent/cli/templates/ui/ui_utils.py
dp/agent/cli/templates/ui/websocket-server.py
dp/agent/cli/templates/ui/api/__init__.py
dp/agent/cli/templates/ui/api/config.py
dp/agent/cli/templates/ui/api/constants.py
dp/agent/cli/templates/ui/api/debug.py
dp/agent/cli/templates/ui/api/files.py
dp/agent/cli/templates/ui/api/files_upload.py
dp/agent/cli/templates/ui/api/files_user.py
dp/agent/cli/templates/ui/api/messages.py
dp/agent/cli/templates/ui/api/projects.py
dp/agent/cli/templates/ui/api/sessions.py
dp/agent/cli/templates/ui/api/utils.py
dp/agent/cli/templates/ui/api/websocket.py
dp/agent/cli/templates/ui/config/__init__.py
dp/agent/cli/templates/ui/config/agent_config.py
dp/agent/cli/templates/ui/frontend/index.html
dp/agent/cli/templates/ui/frontend/package.json
dp/agent/cli/templates/ui/frontend/tsconfig.json
dp/agent/cli/templates/ui/frontend/tsconfig.node.json
dp/agent/cli/templates/ui/frontend/vite.config.ts
dp/agent/cli/templates/ui/frontend/ui-static/index.html
dp/agent/cli/templates/ui/frontend/ui-static/assets/index-DdAmKhul.js
dp/agent/cli/templates/ui/frontend/ui-static/assets/index-DfN2raU9.css
dp/agent/cli/templates/ui/scripts/build_ui.py
dp/agent/cli/templates/ui/server/__init__.py
dp/agent/cli/templates/ui/server/app.py
dp/agent/cli/templates/ui/server/connection.py
bohr_agent_sdk-0.1.122.dist-info/METADATA
bohr_agent_sdk-0.1.122.dist-info/WHEEL
bohr_agent_sdk-0.1.122.dist-info/entry_points.txt
bohr_agent_sdk-0.1.122.dist-info/top_level.txt
bohr_agent_sdk-0.1.122.dist-info/RECORD
