Metadata-Version: 2.4
Name: bohr-agent-sdk
Version: 0.1.122
Summary: SDK for scientific agents
Home-page: https://github.com/dptech-corp/bohr-agent-sdk/
Author: DP Technology
Maintainer-email: liupeng <liupeng@dp.tech>, zjgemi <liuxzj@dp.tech>
License: MIT
Project-URL: Homepage, https://github.com/dptech-corp/bohr-agent-sdk
Project-URL: repository, https://github.com/dptech-corp/bohr-agent-sdk
Project-URL: Bug Reports, https://github.com/dptech-corp/bohr-agent-sdk/issues
Keywords: agent SDK,AI for science
Classifier: License :: OSI Approved :: MIT License
Classifier: Programming Language :: Python :: 3
Classifier: Programming Language :: Python :: 3.10
Classifier: Programming Language :: Python :: 3.11
Classifier: Programming Language :: Python :: 3.12
Classifier: Programming Language :: Python :: 3.13
Requires-Python: >=3.10
Requires-Dist: click>=8.0.0
Requires-Dist: mcp>=1.17.0
Requires-Dist: python-dotenv>=1.0.0
Requires-Dist: typing-extensions>=4.8.0
Requires-Dist: dpdispatcher>=0.6.8
Requires-Dist: lbg>=1.2.29
Requires-Dist: jsonpickle>=3.0.3
Requires-Dist: psutil>=5.9.6
Requires-Dist: paho-mqtt>=2.1.0
Requires-Dist: redis>=6.2.0
Requires-Dist: twine>=6.1.0
Requires-Dist: build>=1.2.2.post1
Requires-Dist: cloudpickle
Requires-Dist: watchdog>=6.0.0
Requires-Dist: fastapi>=0.116.0
Requires-Dist: bohrium-open-sdk
Provides-Extra: device
Requires-Dist: pywinauto-recorder>=0.1.0; extra == "device"
Provides-Extra: cloud
Requires-Dist: paho-mqtt>=1.6.1; extra == "cloud"
Requires-Dist: redis>=5.0.1; extra == "cloud"
Requires-Dist: aiohttp>=3.9.1; extra == "cloud"
Provides-Extra: dev
Requires-Dist: pytest>=7.4.0; extra == "dev"
Requires-Dist: pytest-asyncio>=0.23.0; extra == "dev"
Requires-Dist: pytest-cov>=4.1.0; extra == "dev"
Requires-Dist: black>=23.11.0; extra == "dev"
Requires-Dist: isort>=5.12.0; extra == "dev"
Requires-Dist: mypy>=1.7.0; extra == "dev"
Requires-Dist: pylint>=3.0.0; extra == "dev"
Requires-Dist: google-adk; extra == "dev"
Provides-Extra: docs
Requires-Dist: sphinx>=7.2.0; extra == "docs"
Requires-Dist: sphinx-rtd-theme>=1.3.0; extra == "docs"
Provides-Extra: all
Requires-Dist: bohr-agent-sdk[bohrium,cloud,dev,device,dispatcher,docs]; extra == "all"
Dynamic: home-page
Dynamic: requires-python
